no_exceptions/__init__.py
no_exceptions/_all.py
no_exceptions-0.1.0.dist-info/LICENSE
no_exceptions-0.1.0.dist-info/METADATA
no_exceptions-0.1.0.dist-info/WHEEL
no_exceptions-0.1.0.dist-info/RECORD
