Metadata-Version: 2.1
Name: no-exceptions
Version: 0.1.0
Summary: Errors as values for Python.
Author: Vasiliy Spassky
Author-email: spassky99@gmail.com
Requires-Python: >=3.8,<4.0
Classifier: License :: OSI Approved :: MIT License
Classifier: Operating System :: OS Independent
Classifier: Programming Language :: Python :: 3
Classifier: Programming Language :: Python :: 3.8
Classifier: Programming Language :: Python :: 3.9
Classifier: Programming Language :: Python :: 3.10
Classifier: Programming Language :: Python :: 3.11
Classifier: Programming Language :: Python :: 3.12
Classifier: Programming Language :: Python :: 3.13
Project-URL: Homepage, https://github.com/spassky99/no-exceptions
Project-URL: Issues, https://github.com/spassky99/no-exceptions/issues
